{"cameraMode":{"drawMode":0,"name":"Shaded","section":"Shading Mode"},"sceneLighting":false,"audioPlay":false,"sceneViewState":{"showFog":true,"showMaterialUpdate":false,"showSkybox":false,"showFlares":true,"showImageEffects":true,"showParticleSystems":true},"in2DMode":false,"pivot":{"x":-0.1037420704960823,"y":419.7225341796875,"z":-4.519836902618408},"rotation":{"x":0.33469676971435549,"y":-0.597669780254364,"z":0.3016429543495178,"w":0.6631642580032349},"size":21.564441680908204,"orthographic":false}